jl95/java/__init__.py
jl95/java/util.py
jl95/java/words.py
jl95/java/handlers/__init__.py
jl95/java/handlers/entity/__init__.py
jl95/java/handlers/entity/builder/__init__.py
jl95/java/handlers/entity/builder/exc.py
jl95/java/handlers/line/__init__.py
jl95/java/handlers/part/__init__.py
jl95/java/model/__init__.py
jl95/java/parsers/__init__.py
jl95/java/parsers/annotation/__init__.py
jl95/java/parsers/annotation/exc.py
jl95/java/parsers/annotation/state.py
jl95/java/parsers/body/__init__.py
jl95/java/parsers/body/exc.py
jl95/java/parsers/body/state.py
jl95/java/parsers/callargs/__init__.py
jl95/java/parsers/callargs/exc.py
jl95/java/parsers/callargs/state.py
jl95/java/parsers/entity/__init__.py
jl95/java/parsers/entity/exc.py
jl95/java/parsers/entity/state.py
jl95/java/parsers/expr/__init__.py
jl95/java/parsers/expr/raw/__init__.py
jl95/java/parsers/expr/raw/exc.py
jl95/java/parsers/expr/raw/state.py
jl95/java/parsers/generics/__init__.py
jl95/java/parsers/generics/exc.py
jl95/java/parsers/generics/state.py
jl95/java/parsers/import_/__init__.py
jl95/java/parsers/import_/exc.py
jl95/java/parsers/import_/state.py
jl95/java/parsers/name/__init__.py
jl95/java/parsers/name/exc.py
jl95/java/parsers/name/state.py
jl95/java/parsers/package/__init__.py
jl95/java/parsers/package/exc.py
jl95/java/parsers/package/state.py
jl95/java/parsers/part/__init__.py
jl95/java/parsers/part/exc.py
jl95/java/parsers/part/state.py
jl95/java/parsers/signature/__init__.py
jl95/java/parsers/signature/exc.py
jl95/java/parsers/signature/state.py
jl95/java/parsers/type/__init__.py
jl95/java/parsers/type/exc.py
jl95/java/parsers/type/state.py
jl95terceira/java/__init__.py
jl95terceira/java/util.py
jl95terceira/java/words.py
jl95terceira/java/handlers/__init__.py
jl95terceira/java/handlers/entity/__init__.py
jl95terceira/java/handlers/entity/builder/__init__.py
jl95terceira/java/handlers/entity/builder/exc.py
jl95terceira/java/handlers/line/__init__.py
jl95terceira/java/handlers/part/__init__.py
jl95terceira_java-0.3.4.dist-info/METADATA
jl95terceira_java-0.3.4.dist-info/WHEEL
jl95terceira_java-0.3.4.dist-info/RECORD
