Metadata-Version: 2.4
Name: jl95terceira_java
Version: 0.3.4
Summary: Java parser
Project-URL: Homepage, https://github.com/jl95terceira/project-pyjava
Project-URL: Issues, https://github.com/jl95terceira/project-pyjava/issues
Author-email: Joao Luis Ornelas da Silva <jl95terceira@gmail.com>
Classifier: License :: OSI Approved :: MIT License
Classifier: Operating System :: OS Independent
Classifier: Programming Language :: Python :: 3
Requires-Python: >=3.12
Requires-Dist: jl95terceira-batteries>=1.3.1
